SNOOTY/__init__.py
SNOOTY_TS-0.1.0.dist-info/LICENSE
SNOOTY_TS-0.1.0.dist-info/METADATA
SNOOTY_TS-0.1.0.dist-info/WHEEL
SNOOTY_TS-0.1.0.dist-info/top_level.txt
SNOOTY_TS-0.1.0.dist-info/RECORD
