Metadata-Version: 2.1
Name: SNOOTY-TS
Version: 0.1.0
Summary: smoothing and evaluation for data analysis
Home-page: https://github.com/yuri-gama/SNOOTY
Author: Yuri Gama de Araujo
Author-email: yurigama.t23@gmail.com
License: UNKNOWN
Project-URL: Bug Tracker, https://github.com/yuri-gama/SNOOTY/issues
Platform: UNKNOWN
Classifier: Programming Language :: Python :: 3
Classifier: License :: OSI Approved :: MIT License
Classifier: Operating System :: OS Independent
Requires-Python: >=3.6
License-File: LICENSE
Requires-Dist: rpy2
Requires-Dist: pandas
